{
    "unicast": "0.0.0.0",
    "logging": {
        "level": "info",
        "console": "true"
    },
    "applications": [
        {
            "name": "vsomeip-client",
            "id": "0x0002"
        }
    ],
    "services": [
        {
            "service": "0x4010",
            "instance": "0x0001",
            "unreliable": "30509"
        }
    ],
    "routing": "vsomeip-client",
    "service-discovery": {
        "enable": "true",
        "multicast": "239.224.224.224",
        "port": "30490",
        "protocol": "udp",
        "initial_delay_min": "10",
        "initial_delay_max": "100",
        "repetitions_base_delay": "200",
        "repetitions_max": "3",
        "ttl": "3",
        "cyclic_offer_delay": "1000"
    }
}
